graphene_django_plus/__init__.py
graphene_django_plus/exceptions.py
graphene_django_plus/fields.py
graphene_django_plus/input_types.py
graphene_django_plus/models.py
graphene_django_plus/mutations.py
graphene_django_plus/perms.py
graphene_django_plus/queries.py
graphene_django_plus/schema.py
graphene_django_plus/settings.py
graphene_django_plus/types.py
graphene_django_plus/utils.py
graphene_django_plus/views.py
graphene_django_plus-5.1.dist-info/LICENSE
graphene_django_plus-5.1.dist-info/METADATA
graphene_django_plus-5.1.dist-info/WHEEL
graphene_django_plus-5.1.dist-info/RECORD
