Metadata-Version: 2.1
Name: graphene-django-plus
Version: 5.1
Summary: Tools to easily create permissioned CRUD endpoints in graphene.
Home-page: https://github.com/0soft/graphene-django-plus
License: MIT
Keywords: graphene,django,graphql,crud,permissions
Author: Thiago Bellini Ribeiro
Author-email: thiago@bellini.dev
Requires-Python: >=3.8,<4.0
Classifier: Development Status :: 5 - Production/Stable
Classifier: Environment :: Web Environment
Classifier: Framework :: Django
Classifier: Framework :: Django :: 3.2
Classifier: Framework :: Django :: 4.0
Classifier: Framework :: Django :: 4.1
Classifier: Framework :: Django :: 4.2
Classifier: Intended Audience :: Developers
Classifier: License :: OSI Approved :: MIT License
Classifier: Operating System :: OS Independent
Classifier: Programming Language :: Python
Classifier: Programming Language :: Python :: 3
Classifier: Programming Language :: Python :: 3.8
Classifier: Programming Language :: Python :: 3.9
Classifier: Programming Language :: Python :: 3.10
Classifier: Programming Language :: Python :: 3.11
Requires-Dist: django (>=3.2)
Requires-Dist: graphene-django (>=3.1.2)
Project-URL: Documentation, https://graphene-django-plus.readthedocs.io
Project-URL: Repository, https://github.com/0soft/graphene-django-plus
